magic/__init__.py
magic/cli.py
magic_pure-0.1.0.dist-info/LICENSE
magic_pure-0.1.0.dist-info/METADATA
magic_pure-0.1.0.dist-info/WHEEL
magic_pure-0.1.0.dist-info/entry_points.txt
magic_pure-0.1.0.dist-info/top_level.txt
magic_pure-0.1.0.dist-info/RECORD
